status_check_runner/__init__.py
status_check_runner/__main__.py
status_check_runner/argparse.py
status_check_runner/checkers/__init__.py
status_check_runner/checkers/default.py
status_check_runner/checkers/python.py
status_check_runner/checkers/terraform.py
status_check_runner/checkers/typescript.py
status_check_runner/config.py
status_check_runner/dependencies.py
status_check_runner/execute.py
status_check_runner/reporters/__init__.py
status_check_runner/reporters/console.py
status_check_runner/reporters/github_actions.py
status_check_runner-0.2.0.dist-info/METADATA
status_check_runner-0.2.0.dist-info/WHEEL
status_check_runner-0.2.0.dist-info/RECORD
