Metadata-Version: 2.1
Name: status-check-runner
Version: 0.2.0
Summary: Status check runner
Author: William Sawyer
Author-email: william@situ.com.au
Requires-Python: >=3.12,<4.0
Classifier: Programming Language :: Python :: 3
Classifier: Programming Language :: Python :: 3.12
Requires-Dist: actions-toolkit (>=0.1.15,<0.2.0)
Requires-Dist: jsonref (>=1.1.0,<2.0.0)
Requires-Dist: pydantic (>=2.8.2,<3.0.0)
